odoo/addons/sale_report_margin/README.rst
odoo/addons/sale_report_margin/__init__.py
odoo/addons/sale_report_margin/__manifest__.py
odoo/addons/sale_report_margin/i18n/pt.po
odoo/addons/sale_report_margin/i18n/pt_BR.po
odoo/addons/sale_report_margin/i18n/sale_report_margin.pot
odoo/addons/sale_report_margin/readme/CONTRIBUTORS.rst
odoo/addons/sale_report_margin/readme/DESCRIPTION.rst
odoo/addons/sale_report_margin/readme/ROADMAP.rst
odoo/addons/sale_report_margin/readme/USAGE.rst
odoo/addons/sale_report_margin/reports/__init__.py
odoo/addons/sale_report_margin/reports/sale_report.py
odoo/addons/sale_report_margin/static/description/icon.png
odoo/addons/sale_report_margin/static/description/index.html
odoo12_addon_sale_report_margin-12.0.1.0.1.dist-info/METADATA
odoo12_addon_sale_report_margin-12.0.1.0.1.dist-info/WHEEL
odoo12_addon_sale_report_margin-12.0.1.0.1.dist-info/top_level.txt
odoo12_addon_sale_report_margin-12.0.1.0.1.dist-info/RECORD
